nivo/__init__.py
nivo/db.py
nivo/fields.py
nivo/utils.py
nivo-1.0.0.dist-info/METADATA
nivo-1.0.0.dist-info/WHEEL
nivo-1.0.0.dist-info/entry_points.txt
nivo-1.0.0.dist-info/top_level.txt
nivo-1.0.0.dist-info/RECORD
