Metadata-Version: 2.4
Name: nivo
Version: 1.0.0
Summary: Nivo ORM - A lightweight async ORM for Python using SQLite and aiosqlite.
Home-page: https://github.com/Mahdy-Ahmadi/nivo
Download-URL: https://github.com/Mahdy-Ahmadi/nivo/archive/refs/tags/v1.0.0.zip
Author: Mahdi Ahmadi
Author-email: mahdiahmadi.1208@gmail.com
Maintainer: Mahdi Ahmadi
Maintainer-email: mahdiahmadi.1208@gmail.com
License: MIT
Project-URL: Bug Tracker, https://github.com/Mahdy-Ahmadi/nivo/issues
Project-URL: Documentation, https://github.com/Mahdy-Ahmadi/nivo#readme
Project-URL: Source Code, https://github.com/Mahdy-Ahmadi/nivo
Keywords: orm async sqlite database nivo
Classifier: Development Status :: 4 - Beta
Classifier: Intended Audience :: Developers
Classifier: Programming Language :: Python :: 3
Classifier: Programming Language :: Python :: 3.8
Classifier: Programming Language :: Python :: 3.9
Classifier: Programming Language :: Python :: 3.10
Classifier: Programming Language :: Python :: 3.11
Classifier: License :: OSI Approved :: MIT License
Classifier: Operating System :: OS Independent
Classifier: Topic :: Database
Classifier: Topic :: Software Development :: Libraries
Classifier: Natural Language :: Persian
Requires-Python: >=3.7
Requires-Dist: aiosqlite
Dynamic: author
Dynamic: author-email
Dynamic: classifier
Dynamic: description
Dynamic: description-content-type
Dynamic: download-url
Dynamic: home-page
Dynamic: keywords
Dynamic: license
Dynamic: maintainer
Dynamic: maintainer-email
Dynamic: project-url
Dynamic: requires-dist
Dynamic: requires-python
Dynamic: summary
